visualgo/__init__.py
visualgo/__main__.py
visualgo/logic/__init__.py
visualgo/logic/controller.py
visualgo/logic/controller_callbacks.py
visualgo/logic/types.py
visualgo/logic/debugger/__init__.py
visualgo/logic/debugger/debugger.py
visualgo/logic/debugger/py_debugger.py
visualgo/logic/debugger/types.py
visualgo/logic/debugger/__private/__init__.py
visualgo/logic/debugger/__private/bdb_layer.py
visualgo/logic/debugger/__private/comm_api/__init__.py
visualgo/logic/debugger/__private/comm_api/from_worker.py
visualgo/logic/debugger/__private/comm_api/to_worker.py
visualgo/logic/debugger/__private/comm_impl/__init__.py
visualgo/logic/debugger/__private/comm_impl/python_process_from_worker.py
visualgo/logic/debugger/__private/comm_impl/python_process_to_worker.py
visualgo/logic/static/__init__.py
visualgo/logic/static/static_analysis.py
visualgo/logic/static/types.py
visualgo/logic/ui/__init__.py
visualgo/logic/ui/types.py
visualgo/logic/ui/ui_callbacks.py
visualgo/structures/Array.py
visualgo/structures/BinaryTreeNode.py
visualgo/structures/BinaryTreeNodeBack.py
visualgo/structures/DoublyLinkedList.py
visualgo/structures/Graph.py
visualgo/structures/LinkedList.py
visualgo/structures/List.py
visualgo/structures/Node.py
visualgo/structures/Queue.py
visualgo/structures/Set.py
visualgo/structures/Stack.py
visualgo/structures/Tree.py
visualgo/structures/TreeNode.py
visualgo/structures/TwoWayNode.py
visualgo/structures/__init__.py
visualgo-2024.5.15.dist-info/LICENSE
visualgo-2024.5.15.dist-info/METADATA
visualgo-2024.5.15.dist-info/WHEEL
visualgo-2024.5.15.dist-info/top_level.txt
visualgo-2024.5.15.dist-info/RECORD
