Metadata-Version: 2.1
Name: visualgo
Version: 2024.5.15
Summary: Enjoy classic datatypes and debug user python code
Author: PFA-Visualgo
License: MIT License
Project-URL: Homepage, https://github.com/PFA-Visualgo/Visualgo-PyPI
Project-URL: Issues, https://github.com/PFA-Visualgo/Visualgo-PyPI/issues
Keywords: visualgo,structure,types,debugger
Classifier: Intended Audience :: Developers
Classifier: License :: OSI Approved :: MIT License
Classifier: Programming Language :: Python
Classifier: Programming Language :: Python :: 3
Requires-Python: >=3.9
License-File: LICENSE
Provides-Extra: dev
Requires-Dist: black ; extra == 'dev'
Requires-Dist: bumpver ; extra == 'dev'
Requires-Dist: isort ; extra == 'dev'
Requires-Dist: pip-tools ; extra == 'dev'
Requires-Dist: pytest ; extra == 'dev'
Requires-Dist: pytest-cov ; extra == 'dev'
